bookmarks_parser/__init__.py
bookmarks_parser/bookmarks_parser.py
bookmarks_parser-0.1.3.dist-info/WHEEL
bookmarks_parser-0.1.3.dist-info/METADATA
bookmarks_parser-0.1.3.dist-info/RECORD
